MT_PY_ErrorLogging/MT_Errorlogging.py
MT_PY_ErrorLogging/__init__.py
MT_PY_ErrorLogging/testcode.py
MT_PY_ErrorLogging-0.0.1.dist-info/LICENSE.txt
MT_PY_ErrorLogging-0.0.1.dist-info/METADATA
MT_PY_ErrorLogging-0.0.1.dist-info/WHEEL
MT_PY_ErrorLogging-0.0.1.dist-info/top_level.txt
MT_PY_ErrorLogging-0.0.1.dist-info/RECORD
